[
    {
        "jmhVersion" : "1.37",
        "benchmark" : "io.prometheus.metrics.benchmarks.CounterBenchmark.codahaleIncNoLabels",
        "mode" : "thrpt",
        "threads" : 4,
        "forks" : 3,
        "jvm" : "/home/runner/.local/share/mise/installs/java/temurin-25.0.2+10.0.LTS/bin/java",
        "jvmArgs" : [
        ],
        "jdkVersion" : "25.0.2",
        "vmName" : "OpenJDK 64-Bit Server VM",
        "vmVersion" : "25.0.2+10-LTS",
        "warmupIterations" : 3,
        "warmupTime" : "10 s",
        "warmupBatchSize" : 1,
        "measurementIterations" : 5,
        "measurementTime" : "10 s",
        "measurementBatchSize" : 1,
        "primaryMetric" : {
            "score" : 50037.074877358355,
            "scoreError" : 503.0426590066618,
            "scoreConfidence" : [
                49534.03221835169,
                50540.11753636502
            ],
            "scorePercentiles" : {
                "0.0" : 49335.0848040376,
                "50.0" : 50323.55424961706,
                "90.0" : 50433.23333540846,
                "95.0" : 50435.26944276468,
                "99.0" : 50435.26944276468,
                "99.9" : 50435.26944276468,
                "99.99" : 50435.26944276468,
                "99.999" : 50435.26944276468,
                "99.9999" : 50435.26944276468,
                "100.0" : 50435.26944276468
            },
            "scoreUnit" : "ops/s",
            "rawData" : [
                [
                    50435.26944276468,
                    50431.79578787477,
                    50431.87593050432,
                    50323.55424961706,
                    50410.77836845118
                ],
                [
                    49473.033384184004,
                    49335.0848040376,
                    49388.251359128175,
                    49437.77669833619,
                    49407.92897207298
                ],
                [
                    50394.871733347245,
                    50420.85466685948,
                    50342.49674152782,
                    50264.98559848263,
                    50057.565423187094
                ]
            ]
        },
        "secondaryMetrics" : {
        }
    },
    {
        "jmhVersion" : "1.37",
        "benchmark" : "io.prometheus.metrics.benchmarks.CounterBenchmark.openTelemetryAdd",
        "mode" : "thrpt",
        "threads" : 4,
        "forks" : 3,
        "jvm" : "/home/runner/.local/share/mise/installs/java/temurin-25.0.2+10.0.LTS/bin/java",
        "jvmArgs" : [
        ],
        "jdkVersion" : "25.0.2",
        "vmName" : "OpenJDK 64-Bit Server VM",
        "vmVersion" : "25.0.2+10-LTS",
        "warmupIterations" : 3,
        "warmupTime" : "10 s",
        "warmupBatchSize" : 1,
        "measurementIterations" : 5,
        "measurementTime" : "10 s",
        "measurementBatchSize" : 1,
        "primaryMetric" : {
            "score" : 1326.5634980814114,
            "scoreError" : 7.441752482880509,
            "scoreConfidence" : [
                1319.1217455985309,
                1334.0052505642918
            ],
            "scorePercentiles" : {
                "0.0" : 1317.4565935716741,
                "50.0" : 1328.029153007502,
                "90.0" : 1334.3996907981682,
                "95.0" : 1334.6410780685565,
                "99.0" : 1334.6410780685565,
                "99.9" : 1334.6410780685565,
                "99.99" : 1334.6410780685565,
                "99.999" : 1334.6410780685565,
                "99.9999" : 1334.6410780685565,
                "100.0" : 1334.6410780685565
            },
            "scoreUnit" : "ops/s",
            "rawData" : [
                [
                    1328.2315473886142,
                    1328.1048934586383,
                    1328.029153007502,
                    1327.581898837363,
                    1327.8644319932464
                ],
                [
                    1334.6410780685565,
                    1334.027510307737,
                    1333.6242865631853,
                    1333.4804898958382,
                    1334.2387659512428
                ],
                [
                    1318.0230067307905,
                    1317.698796897755,
                    1317.5240772295317,
                    1317.925941319497,
                    1317.4565935716741
                ]
            ]
        },
        "secondaryMetrics" : {
        }
    },
    {
        "jmhVersion" : "1.37",
        "benchmark" : "io.prometheus.metrics.benchmarks.CounterBenchmark.openTelemetryInc",
        "mode" : "thrpt",
        "threads" : 4,
        "forks" : 3,
        "jvm" : "/home/runner/.local/share/mise/installs/java/temurin-25.0.2+10.0.LTS/bin/java",
        "jvmArgs" : [
        ],
        "jdkVersion" : "25.0.2",
        "vmName" : "OpenJDK 64-Bit Server VM",
        "vmVersion" : "25.0.2+10-LTS",
        "warmupIterations" : 3,
        "warmupTime" : "10 s",
        "warmupBatchSize" : 1,
        "measurementIterations" : 5,
        "measurementTime" : "10 s",
        "measurementBatchSize" : 1,
        "primaryMetric" : {
            "score" : 1281.1554765235048,
            "scoreError" : 37.67782723661976,
            "scoreConfidence" : [
                1243.477649286885,
                1318.8333037601246
            ],
            "scorePercentiles" : {
                "0.0" : 1244.3341906549635,
                "50.0" : 1272.4620236650267,
                "90.0" : 1327.2632038569927,
                "95.0" : 1327.2636847008994,
                "99.0" : 1327.2636847008994,
                "99.9" : 1327.2636847008994,
                "99.99" : 1327.2636847008994,
                "99.999" : 1327.2636847008994,
                "99.9999" : 1327.2636847008994,
                "100.0" : 1327.2636847008994
            },
            "scoreUnit" : "ops/s",
            "rawData" : [
                [
                    1244.3341906549635,
                    1244.5276274084156,
                    1244.3761447401228,
                    1244.769160627868,
                    1244.7280280110458
                ],
                [
                    1325.7472890304111,
                    1325.650480884647,
                    1327.2628832943883,
                    1327.2636847008994,
                    1326.790598280225
                ],
                [
                    1272.4620236650267,
                    1271.7205752435705,
                    1272.2562365807999,
                    1272.5480810700979,
                    1272.8951436600908
                ]
            ]
        },
        "secondaryMetrics" : {
        }
    },
    {
        "jmhVersion" : "1.37",
        "benchmark" : "io.prometheus.metrics.benchmarks.CounterBenchmark.openTelemetryIncNoLabels",
        "mode" : "thrpt",
        "threads" : 4,
        "forks" : 3,
        "jvm" : "/home/runner/.local/share/mise/installs/java/temurin-25.0.2+10.0.LTS/bin/java",
        "jvmArgs" : [
        ],
        "jdkVersion" : "25.0.2",
        "vmName" : "OpenJDK 64-Bit Server VM",
        "vmVersion" : "25.0.2+10-LTS",
        "warmupIterations" : 3,
        "warmupTime" : "10 s",
        "warmupBatchSize" : 1,
        "measurementIterations" : 5,
        "measurementTime" : "10 s",
        "measurementBatchSize" : 1,
        "primaryMetric" : {
            "score" : 1183.978471690251,
            "scoreError" : 18.13936331102684,
            "scoreConfidence" : [
                1165.839108379224,
                1202.1178350012779
            ],
            "scorePercentiles" : {
                "0.0" : 1168.581511254426,
                "50.0" : 1176.5339265594216,
                "90.0" : 1206.9095956817566,
                "95.0" : 1207.0419965286455,
                "99.0" : 1207.0419965286455,
                "99.9" : 1207.0419965286455,
                "99.99" : 1207.0419965286455,
                "99.999" : 1207.0419965286455,
                "99.9999" : 1207.0419965286455,
                "100.0" : 1207.0419965286455
            },
            "scoreUnit" : "ops/s",
            "rawData" : [
                [
                    1206.5401802240854,
                    1206.5295509017262,
                    1206.8075997386404,
                    1207.0419965286455,
                    1206.8213284504973
                ],
                [
                    1168.6501331570223,
                    1168.581511254426,
                    1168.8193833134644,
                    1169.0982538977157,
                    1169.0768512872892
                ],
                [
                    1177.033273414833,
                    1176.5339265594216,
                    1176.591519665641,
                    1175.8527556867675,
                    1175.6988112735887
                ]
            ]
        },
        "secondaryMetrics" : {
        }
    },
    {
        "jmhVersion" : "1.37",
        "benchmark" : "io.prometheus.metrics.benchmarks.CounterBenchmark.prometheusAdd",
        "mode" : "thrpt",
        "threads" : 4,
        "forks" : 3,
        "jvm" : "/home/runner/.local/share/mise/installs/java/temurin-25.0.2+10.0.LTS/bin/java",
        "jvmArgs" : [
        ],
        "jdkVersion" : "25.0.2",
        "vmName" : "OpenJDK 64-Bit Server VM",
        "vmVersion" : "25.0.2+10-LTS",
        "warmupIterations" : 3,
        "warmupTime" : "10 s",
        "warmupBatchSize" : 1,
        "measurementIterations" : 5,
        "measurementTime" : "10 s",
        "measurementBatchSize" : 1,
        "primaryMetric" : {
            "score" : 51048.818409449465,
            "scoreError" : 756.3126331790621,
            "scoreConfidence" : [
                50292.5057762704,
                51805.13104262853
            ],
            "scorePercentiles" : {
                "0.0" : 49869.52431967482,
                "50.0" : 51418.24230600189,
                "90.0" : 51674.206287000256,
                "95.0" : 51677.058481676715,
                "99.0" : 51677.058481676715,
                "99.9" : 51677.058481676715,
                "99.99" : 51677.058481676715,
                "99.999" : 51677.058481676715,
                "99.9999" : 51677.058481676715,
                "100.0" : 51677.058481676715
            },
            "scoreUnit" : "ops/s",
            "rawData" : [
                [
                    50192.055066611545,
                    49869.52431967482,
                    50176.45145293404,
                    50065.77638870001,
                    50179.6300775522
                ],
                [
                    51668.38629606185,
                    51496.92059365383,
                    51631.45016536303,
                    51677.058481676715,
                    51672.304823882616
                ],
                [
                    51403.154103878944,
                    51441.85058448833,
                    51415.37245363498,
                    51418.24230600189,
                    51424.09902762741
                ]
            ]
        },
        "secondaryMetrics" : {
        }
    },
    {
        "jmhVersion" : "1.37",
        "benchmark" : "io.prometheus.metrics.benchmarks.CounterBenchmark.prometheusInc",
        "mode" : "thrpt",
        "threads" : 4,
        "forks" : 3,
        "jvm" : "/home/runner/.local/share/mise/installs/java/temurin-25.0.2+10.0.LTS/bin/java",
        "jvmArgs" : [
        ],
        "jdkVersion" : "25.0.2",
        "vmName" : "OpenJDK 64-Bit Server VM",
        "vmVersion" : "25.0.2+10-LTS",
        "warmupIterations" : 3,
        "warmupTime" : "10 s",
        "warmupBatchSize" : 1,
        "measurementIterations" : 5,
        "measurementTime" : "10 s",
        "measurementBatchSize" : 1,
        "primaryMetric" : {
            "score" : 65398.72862790809,
            "scoreError" : 1764.29944867412,
            "scoreConfidence" : [
                63634.429179233965,
                67163.02807658221
            ],
            "scorePercentiles" : {
                "0.0" : 63032.060301365214,
                "50.0" : 66462.46141011329,
                "90.0" : 66620.00748889435,
                "95.0" : 66623.50732428483,
                "99.0" : 66623.50732428483,
                "99.9" : 66623.50732428483,
                "99.99" : 66623.50732428483,
                "99.999" : 66623.50732428483,
                "99.9999" : 66623.50732428483,
                "100.0" : 66623.50732428483
            },
            "scoreUnit" : "ops/s",
            "rawData" : [
                [
                    66529.0414186112,
                    66502.16134155,
                    66504.80849048129,
                    66343.46038063262,
                    66459.07894077418
                ],
                [
                    66607.94750990382,
                    66462.46141011329,
                    66597.7576605641,
                    66623.50732428483,
                    66617.6742653007
                ],
                [
                    63162.55396338657,
                    63164.5846274268,
                    63194.29735491367,
                    63179.53442931304,
                    63032.060301365214
                ]
            ]
        },
        "secondaryMetrics" : {
        }
    },
    {
        "jmhVersion" : "1.37",
        "benchmark" : "io.prometheus.metrics.benchmarks.CounterBenchmark.prometheusNoLabelsInc",
        "mode" : "thrpt",
        "threads" : 4,
        "forks" : 3,
        "jvm" : "/home/runner/.local/share/mise/installs/java/temurin-25.0.2+10.0.LTS/bin/java",
        "jvmArgs" : [
        ],
        "jdkVersion" : "25.0.2",
        "vmName" : "OpenJDK 64-Bit Server VM",
        "vmVersion" : "25.0.2+10-LTS",
        "warmupIterations" : 3,
        "warmupTime" : "10 s",
        "warmupBatchSize" : 1,
        "measurementIterations" : 5,
        "measurementTime" : "10 s",
        "measurementBatchSize" : 1,
        "primaryMetric" : {
            "score" : 57051.4302146542,
            "scoreError" : 350.5687191828755,
            "scoreConfidence" : [
                56700.86149547133,
                57401.99893383708
            ],
            "scorePercentiles" : {
                "0.0" : 56512.264355319625,
                "50.0" : 57193.78650817268,
                "90.0" : 57333.60751979884,
                "95.0" : 57335.541141122376,
                "99.0" : 57335.541141122376,
                "99.9" : 57335.541141122376,
                "99.99" : 57335.541141122376,
                "99.999" : 57335.541141122376,
                "99.9999" : 57335.541141122376,
                "100.0" : 57335.541141122376
            },
            "scoreUnit" : "ops/s",
            "rawData" : [
                [
                    57330.30198663587,
                    57299.143204867556,
                    57193.78650817268,
                    57162.93843115565,
                    57295.68556344655
                ],
                [
                    57169.33910290871,
                    57332.31843891648,
                    57267.0280957159,
                    57325.67182354425,
                    57335.541141122376
                ],
                [
                    56620.46652550698,
                    56654.333154333595,
                    56638.165811095874,
                    56634.46907707089,
                    56512.264355319625
                ]
            ]
        },
        "secondaryMetrics" : {
        }
    },
    {
        "jmhVersion" : "1.37",
        "benchmark" : "io.prometheus.metrics.benchmarks.CounterBenchmark.simpleclientAdd",
        "mode" : "thrpt",
        "threads" : 4,
        "forks" : 3,
        "jvm" : "/home/runner/.local/share/mise/installs/java/temurin-25.0.2+10.0.LTS/bin/java",
        "jvmArgs" : [
        ],
        "jdkVersion" : "25.0.2",
        "vmName" : "OpenJDK 64-Bit Server VM",
        "vmVersion" : "25.0.2+10-LTS",
        "warmupIterations" : 3,
        "warmupTime" : "10 s",
        "warmupBatchSize" : 1,
        "measurementIterations" : 5,
        "measurementTime" : "10 s",
        "measurementBatchSize" : 1,
        "primaryMetric" : {
            "score" : 6147.644288260223,
            "scoreError" : 60.08099560885407,
            "scoreConfidence" : [
                6087.563292651369,
                6207.725283869077
            ],
            "scorePercentiles" : {
                "0.0" : 6093.868601750702,
                "50.0" : 6117.3616904999,
                "90.0" : 6234.809552115302,
                "95.0" : 6236.762672578984,
                "99.0" : 6236.762672578984,
                "99.9" : 6236.762672578984,
                "99.99" : 6236.762672578984,
                "99.999" : 6236.762672578984,
                "99.9999" : 6236.762672578984,
                "100.0" : 6236.762672578984
            },
            "scoreUnit" : "ops/s",
            "rawData" : [
                [
                    6121.245147726359,
                    6117.3616904999,
                    6106.716582884606,
                    6122.404897476047,
                    6105.619648830152
                ],
                [
                    6218.622982674108,
                    6206.387531273094,
                    6221.280036309856,
                    6236.762672578984,
                    6233.50747180618
                ],
                [
                    6102.875759946228,
                    6110.425607609078,
                    6108.928810938876,
                    6108.65688159916,
                    6093.868601750702
                ]
            ]
        },
        "secondaryMetrics" : {
        }
    },
    {
        "jmhVersion" : "1.37",
        "benchmark" : "io.prometheus.metrics.benchmarks.CounterBenchmark.simpleclientInc",
        "mode" : "thrpt",
        "threads" : 4,
        "forks" : 3,
        "jvm" : "/home/runner/.local/share/mise/installs/java/temurin-25.0.2+10.0.LTS/bin/java",
        "jvmArgs" : [
        ],
        "jdkVersion" : "25.0.2",
        "vmName" : "OpenJDK 64-Bit Server VM",
        "vmVersion" : "25.0.2+10-LTS",
        "warmupIterations" : 3,
        "warmupTime" : "10 s",
        "warmupBatchSize" : 1,
        "measurementIterations" : 5,
        "measurementTime" : "10 s",
        "measurementBatchSize" : 1,
        "primaryMetric" : {
            "score" : 6483.1963381856385,
            "scoreError" : 25.25693069726087,
            "scoreConfidence" : [
                6457.939407488378,
                6508.4532688828995
            ],
            "scorePercentiles" : {
                "0.0" : 6446.3984972633525,
                "50.0" : 6485.484398133445,
                "90.0" : 6514.1652055078775,
                "95.0" : 6514.718307086992,
                "99.0" : 6514.718307086992,
                "99.9" : 6514.718307086992,
                "99.99" : 6514.718307086992,
                "99.999" : 6514.718307086992,
                "99.9999" : 6514.718307086992,
                "100.0" : 6514.718307086992
            },
            "scoreUnit" : "ops/s",
            "rawData" : [
                [
                    6513.796471121801,
                    6512.046781499993,
                    6498.126577557087,
                    6513.162655780128,
                    6514.718307086992
                ],
                [
                    6446.3984972633525,
                    6461.591525763901,
                    6461.65847363502,
                    6452.326193048358,
                    6460.45461599359
                ],
                [
                    6485.484398133445,
                    6486.209376598947,
                    6485.360326491998,
                    6485.695892603067,
                    6470.914980206909
                ]
            ]
        },
        "secondaryMetrics" : {
        }
    },
    {
        "jmhVersion" : "1.37",
        "benchmark" : "io.prometheus.metrics.benchmarks.CounterBenchmark.simpleclientNoLabelsInc",
        "mode" : "thrpt",
        "threads" : 4,
        "forks" : 3,
        "jvm" : "/home/runner/.local/share/mise/installs/java/temurin-25.0.2+10.0.LTS/bin/java",
        "jvmArgs" : [
        ],
        "jdkVersion" : "25.0.2",
        "vmName" : "OpenJDK 64-Bit Server VM",
        "vmVersion" : "25.0.2+10-LTS",
        "warmupIterations" : 3,
        "warmupTime" : "10 s",
        "warmupBatchSize" : 1,
        "measurementIterations" : 5,
        "measurementTime" : "10 s",
        "measurementBatchSize" : 1,
        "primaryMetric" : {
            "score" : 6544.3320888631415,
            "scoreError" : 96.29716749229183,
            "scoreConfidence" : [
                6448.03492137085,
                6640.629256355433
            ],
            "scorePercentiles" : {
                "0.0" : 6469.159888520001,
                "50.0" : 6487.425158034466,
                "90.0" : 6670.528631981446,
                "95.0" : 6670.895042156975,
                "99.0" : 6670.895042156975,
                "99.9" : 6670.895042156975,
                "99.99" : 6670.895042156975,
                "99.999" : 6670.895042156975,
                "99.9999" : 6670.895042156975,
                "100.0" : 6670.895042156975
            },
            "scoreUnit" : "ops/s",
            "rawData" : [
                [
                    6670.895042156975,
                    6670.094242580594,
                    6653.960712179193,
                    6670.146701293146,
                    6670.284358531093
                ],
                [
                    6473.327661097979,
                    6489.019545234694,
                    6488.357904374141,
                    6485.128809245259,
                    6483.821680875693
                ],
                [
                    6484.209229535304,
                    6484.332470718056,
                    6484.817928570499,
                    6487.425158034466,
                    6469.159888520001
                ]
            ]
        },
        "secondaryMetrics" : {
        }
    },
    {
        "jmhVersion" : "1.37",
        "benchmark" : "io.prometheus.metrics.benchmarks.HistogramBenchmark.openTelemetryClassic",
        "mode" : "thrpt",
        "threads" : 4,
        "forks" : 3,
        "jvm" : "/home/runner/.local/share/mise/installs/java/temurin-25.0.2+10.0.LTS/bin/java",
        "jvmArgs" : [
        ],
        "jdkVersion" : "25.0.2",
        "vmName" : "OpenJDK 64-Bit Server VM",
        "vmVersion" : "25.0.2+10-LTS",
        "warmupIterations" : 3,
        "warmupTime" : "10 s",
        "warmupBatchSize" : 1,
        "measurementIterations" : 5,
        "measurementTime" : "10 s",
        "measurementBatchSize" : 1,
        "primaryMetric" : {
            "score" : 665.4773335918628,
            "scoreError" : 34.56617836112975,
            "scoreConfidence" : [
                630.911155230733,
                700.0435119529926
            ],
            "scorePercentiles" : {
                "0.0" : 641.7795041706474,
                "50.0" : 644.4203827503002,
                "90.0" : 710.0341198067346,
                "95.0" : 710.1368219710091,
                "99.0" : 710.1368219710091,
                "99.9" : 710.1368219710091,
                "99.99" : 710.1368219710091,
                "99.999" : 710.1368219710091,
                "99.9999" : 710.1368219710091,
                "100.0" : 710.1368219710091
            },
            "scoreUnit" : "ops/s",
            "rawData" : [
                [
                    642.3053716122228,
                    642.5955756685973,
                    642.1026533723201,
                    642.6372591213448,
                    641.7795041706474
                ],
                [
                    709.8998054246692,
                    708.7255533946673,
                    709.9656516972182,
                    709.4220195759815,
                    710.1368219710091
                ],
                [
                    643.9867316527377,
                    644.4203827503002,
                    645.1795295590696,
                    644.1933916025018,
                    644.8097523046544
                ]
            ]
        },
        "secondaryMetrics" : {
        }
    },
    {
        "jmhVersion" : "1.37",
        "benchmark" : "io.prometheus.metrics.benchmarks.HistogramBenchmark.openTelemetryExponential",
        "mode" : "thrpt",
        "threads" : 4,
        "forks" : 3,
        "jvm" : "/home/runner/.local/share/mise/installs/java/temurin-25.0.2+10.0.LTS/bin/java",
        "jvmArgs" : [
        ],
        "jdkVersion" : "25.0.2",
        "vmName" : "OpenJDK 64-Bit Server VM",
        "vmVersion" : "25.0.2+10-LTS",
        "warmupIterations" : 3,
        "warmupTime" : "10 s",
        "warmupBatchSize" : 1,
        "measurementIterations" : 5,
        "measurementTime" : "10 s",
        "measurementBatchSize" : 1,
        "primaryMetric" : {
            "score" : 556.0296307345518,
            "scoreError" : 3.710508494622281,
            "scoreConfidence" : [
                552.3191222399295,
                559.7401392291741
            ],
            "scorePercentiles" : {
                "0.0" : 548.8579704405752,
                "50.0" : 558.3444402268378,
                "90.0" : 559.2220730096954,
                "95.0" : 559.8194657074934,
                "99.0" : 559.8194657074934,
                "99.9" : 559.8194657074934,
                "99.99" : 559.8194657074934,
                "99.999" : 559.8194657074934,
                "99.9999" : 559.8194657074934,
                "100.0" : 559.8194657074934
            },
            "scoreUnit" : "ops/s",
            "rawData" : [
                [
                    554.7131020541113,
                    554.5864388646015,
                    554.7287137183686,
                    554.6260391502603,
                    554.3042081597091
                ],
                [
                    559.8194657074934,
                    558.5967880845362,
                    558.3444402268378,
                    548.8579704405752,
                    549.0770351666158
                ],
                [
                    558.6465248415993,
                    558.3956529576692,
                    558.5746697809375,
                    558.3496006537985,
                    558.8238112111634
                ]
            ]
        },
        "secondaryMetrics" : {
        }
    },
    {
        "jmhVersion" : "1.37",
        "benchmark" : "io.prometheus.metrics.benchmarks.HistogramBenchmark.prometheusClassic",
        "mode" : "thrpt",
        "threads" : 4,
        "forks" : 3,
        "jvm" : "/home/runner/.local/share/mise/installs/java/temurin-25.0.2+10.0.LTS/bin/java",
        "jvmArgs" : [
        ],
        "jdkVersion" : "25.0.2",
        "vmName" : "OpenJDK 64-Bit Server VM",
        "vmVersion" : "25.0.2+10-LTS",
        "warmupIterations" : 3,
        "warmupTime" : "10 s",
        "warmupBatchSize" : 1,
        "measurementIterations" : 5,
        "measurementTime" : "10 s",
        "measurementBatchSize" : 1,
        "primaryMetric" : {
            "score" : 4880.363878145175,
            "scoreError" : 873.416881141123,
            "scoreConfidence" : [
                4006.946997004052,
                5753.780759286297
            ],
            "scorePercentiles" : {
                "0.0" : 4070.4051224772343,
                "50.0" : 4605.171566623576,
                "90.0" : 6142.73350133907,
                "95.0" : 6192.1251197514175,
                "99.0" : 6192.1251197514175,
                "99.9" : 6192.1251197514175,
                "99.99" : 6192.1251197514175,
                "99.999" : 6192.1251197514175,
                "99.9999" : 6192.1251197514175,
                "100.0" : 6192.1251197514175
            },
            "scoreUnit" : "ops/s",
            "rawData" : [
                [
                    4164.627054886816,
                    4167.410004181201,
                    4151.602468618395,
                    4167.905577341493,
                    4070.4051224772343
                ],
                [
                    4954.414981500482,
                    6192.1251197514175,
                    6108.521195171436,
                    6109.805755730839,
                    6104.366445472125
                ],
                [
                    4606.130872241925,
                    4602.52013778588,
                    4605.171566623576,
                    4605.3050006233725,
                    4595.146869771417
                ]
            ]
        },
        "secondaryMetrics" : {
        }
    },
    {
        "jmhVersion" : "1.37",
        "benchmark" : "io.prometheus.metrics.benchmarks.HistogramBenchmark.prometheusNative",
        "mode" : "thrpt",
        "threads" : 4,
        "forks" : 3,
        "jvm" : "/home/runner/.local/share/mise/installs/java/temurin-25.0.2+10.0.LTS/bin/java",
        "jvmArgs" : [
        ],
        "jdkVersion" : "25.0.2",
        "vmName" : "OpenJDK 64-Bit Server VM",
        "vmVersion" : "25.0.2+10-LTS",
        "warmupIterations" : 3,
        "warmupTime" : "10 s",
        "warmupBatchSize" : 1,
        "measurementIterations" : 5,
        "measurementTime" : "10 s",
        "measurementBatchSize" : 1,
        "primaryMetric" : {
            "score" : 3063.5637637036866,
            "scoreError" : 278.5765184806044,
            "scoreConfidence" : [
                2784.987245223082,
                3342.140282184291
            ],
            "scorePercentiles" : {
                "0.0" : 2676.7167799989106,
                "50.0" : 3174.6326312231486,
                "90.0" : 3324.2746912064713,
                "95.0" : 3394.044480401693,
                "99.0" : 3394.044480401693,
                "99.9" : 3394.044480401693,
                "99.99" : 3394.044480401693,
                "99.999" : 3394.044480401693,
                "99.9999" : 3394.044480401693,
                "100.0" : 3394.044480401693
            },
            "scoreUnit" : "ops/s",
            "rawData" : [
                [
                    2722.735157849449,
                    2795.250117255231,
                    2713.0681158291936,
                    2692.1397704695996,
                    2676.7167799989106
                ],
                [
                    3230.593474544759,
                    3267.399319715827,
                    3273.4917155974695,
                    3277.761498409657,
                    3274.1975874695827
                ],
                [
                    3115.248080840105,
                    3177.587526567297,
                    3394.044480401693,
                    3174.6326312231486,
                    3168.5901993833763
                ]
            ]
        },
        "secondaryMetrics" : {
        }
    },
    {
        "jmhVersion" : "1.37",
        "benchmark" : "io.prometheus.metrics.benchmarks.HistogramBenchmark.simpleclient",
        "mode" : "thrpt",
        "threads" : 4,
        "forks" : 3,
        "jvm" : "/home/runner/.local/share/mise/installs/java/temurin-25.0.2+10.0.LTS/bin/java",
        "jvmArgs" : [
        ],
        "jdkVersion" : "25.0.2",
        "vmName" : "OpenJDK 64-Bit Server VM",
        "vmVersion" : "25.0.2+10-LTS",
        "warmupIterations" : 3,
        "warmupTime" : "10 s",
        "warmupBatchSize" : 1,
        "measurementIterations" : 5,
        "measurementTime" : "10 s",
        "measurementBatchSize" : 1,
        "primaryMetric" : {
            "score" : 4554.015438222438,
            "scoreError" : 42.3774636125266,
            "scoreConfidence" : [
                4511.637974609912,
                4596.3929018349645
            ],
            "scorePercentiles" : {
                "0.0" : 4483.663004420792,
                "50.0" : 4548.475022783772,
                "90.0" : 4611.179106161853,
                "95.0" : 4614.27371796479,
                "99.0" : 4614.27371796479,
                "99.9" : 4614.27371796479,
                "99.99" : 4614.27371796479,
                "99.999" : 4614.27371796479,
                "99.9999" : 4614.27371796479,
                "100.0" : 4614.27371796479
            },
            "scoreUnit" : "ops/s",
            "rawData" : [
                [
                    4593.588855795309,
                    4592.099648604943,
                    4596.345344729231,
                    4614.27371796479,
                    4609.116031626561
                ],
                [
                    4483.663004420792,
                    4500.51754754825,
                    4519.813434542052,
                    4536.132513001723,
                    4524.829867876692
                ],
                [
                    4539.302320636683,
                    4555.917957485933,
                    4553.024542299439,
                    4548.475022783772,
                    4543.131764020401
                ]
            ]
        },
        "secondaryMetrics" : {
        }
    },
    {
        "jmhVersion" : "1.37",
        "benchmark" : "io.prometheus.metrics.benchmarks.TextFormatUtilBenchmark.openMetricsWriteToByteArray",
        "mode" : "thrpt",
        "threads" : 1,
        "forks" : 3,
        "jvm" : "/home/runner/.local/share/mise/installs/java/temurin-25.0.2+10.0.LTS/bin/java",
        "jvmArgs" : [
        ],
        "jdkVersion" : "25.0.2",
        "vmName" : "OpenJDK 64-Bit Server VM",
        "vmVersion" : "25.0.2+10-LTS",
        "warmupIterations" : 3,
        "warmupTime" : "10 s",
        "warmupBatchSize" : 1,
        "measurementIterations" : 5,
        "measurementTime" : "10 s",
        "measurementBatchSize" : 1,
        "primaryMetric" : {
            "score" : 468359.08619626384,
            "scoreError" : 10111.224017611397,
            "scoreConfidence" : [
                458247.86217865243,
                478470.31021387526
            ],
            "scorePercentiles" : {
                "0.0" : 455823.17302236054,
                "50.0" : 463264.12889609655,
                "90.0" : 482722.2437100949,
                "95.0" : 482843.2199059986,
                "99.0" : 482843.2199059986,
                "99.9" : 482843.2199059986,
                "99.99" : 482843.2199059986,
                "99.999" : 482843.2199059986,
                "99.9999" : 482843.2199059986,
                "100.0" : 482843.2199059986
            },
            "scoreUnit" : "ops/s",
            "rawData" : [
                [
                    461959.74584358535,
                    461254.30360253906,
                    463247.80670614046,
                    463264.12889609655,
                    466287.0197860684
                ],
                [
                    482641.59291282576,
                    482843.2199059986,
                    481093.2702544286,
                    476913.577795156,
                    480602.6087242115
                ],
                [
                    463640.4987994784,
                    462883.49567606684,
                    462210.1042618122,
                    455823.17302236054,
                    460721.7467571896
                ]
            ]
        },
        "secondaryMetrics" : {
        }
    },
    {
        "jmhVersion" : "1.37",
        "benchmark" : "io.prometheus.metrics.benchmarks.TextFormatUtilBenchmark.openMetricsWriteToNull",
        "mode" : "thrpt",
        "threads" : 1,
        "forks" : 3,
        "jvm" : "/home/runner/.local/share/mise/installs/java/temurin-25.0.2+10.0.LTS/bin/java",
        "jvmArgs" : [
        ],
        "jdkVersion" : "25.0.2",
        "vmName" : "OpenJDK 64-Bit Server VM",
        "vmVersion" : "25.0.2+10-LTS",
        "warmupIterations" : 3,
        "warmupTime" : "10 s",
        "warmupBatchSize" : 1,
        "measurementIterations" : 5,
        "measurementTime" : "10 s",
        "measurementBatchSize" : 1,
        "primaryMetric" : {
            "score" : 478788.56122208893,
            "scoreError" : 10953.688361586455,
            "scoreConfidence" : [
                467834.87286050245,
                489742.2495836754
            ],
            "scorePercentiles" : {
                "0.0" : 459064.2227757132,
                "50.0" : 483634.4653112504,
                "90.0" : 487793.73585648683,
                "95.0" : 488286.7853186035,
                "99.0" : 488286.7853186035,
                "99.9" : 488286.7853186035,
                "99.99" : 488286.7853186035,
                "99.999" : 488286.7853186035,
                "99.9999" : 488286.7853186035,
                "100.0" : 488286.7853186035
            },
            "scoreUnit" : "ops/s",
            "rawData" : [
                [
                    486057.7326367591,
                    486599.8790899197,
                    487465.03621507576,
                    483634.4653112504,
                    485709.40871267306
                ],
                [
                    459064.2227757132,
                    460703.8854589243,
                    464447.47602369735,
                    470801.55398569297,
                    477027.74368972884
                ],
                [
                    476870.8475115484,
                    483450.0030637101,
                    484260.2133365699,
                    488286.7853186035,
                    487449.1652014667
                ]
            ]
        },
        "secondaryMetrics" : {
        }
    },
    {
        "jmhVersion" : "1.37",
        "benchmark" : "io.prometheus.metrics.benchmarks.TextFormatUtilBenchmark.prometheusWriteToByteArray",
        "mode" : "thrpt",
        "threads" : 1,
        "forks" : 3,
        "jvm" : "/home/runner/.local/share/mise/installs/java/temurin-25.0.2+10.0.LTS/bin/java",
        "jvmArgs" : [
        ],
        "jdkVersion" : "25.0.2",
        "vmName" : "OpenJDK 64-Bit Server VM",
        "vmVersion" : "25.0.2+10-LTS",
        "warmupIterations" : 3,
        "warmupTime" : "10 s",
        "warmupBatchSize" : 1,
        "measurementIterations" : 5,
        "measurementTime" : "10 s",
        "measurementBatchSize" : 1,
        "primaryMetric" : {
            "score" : 486506.5447142948,
            "scoreError" : 5042.154872781413,
            "scoreConfidence" : [
                481464.38984151336,
                491548.6995870762
            ],
            "scorePercentiles" : {
                "0.0" : 477385.74619443604,
                "50.0" : 488270.87264860194,
                "90.0" : 491274.5023950763,
                "95.0" : 491442.3279398103,
                "99.0" : 491442.3279398103,
                "99.9" : 491442.3279398103,
                "99.99" : 491442.3279398103,
                "99.999" : 491442.3279398103,
                "99.9999" : 491442.3279398103,
                "100.0" : 491442.3279398103
            },
            "scoreUnit" : "ops/s",
            "rawData" : [
                [
                    477385.74619443604,
                    481147.7724956154,
                    478215.3932035426,
                    483914.20796154765,
                    484406.21050278866
                ],
                [
                    484072.2498495822,
                    487476.1679125398,
                    488270.87264860194,
                    488854.4708586288,
                    490240.48179346154
                ],
                [
                    491162.618698587,
                    490145.74690073123,
                    491442.3279398103,
                    490197.30851086386,
                    490666.5952436863
                ]
            ]
        },
        "secondaryMetrics" : {
        }
    },
    {
        "jmhVersion" : "1.37",
        "benchmark" : "io.prometheus.metrics.benchmarks.TextFormatUtilBenchmark.prometheusWriteToNull",
        "mode" : "thrpt",
        "threads" : 1,
        "forks" : 3,
        "jvm" : "/home/runner/.local/share/mise/installs/java/temurin-25.0.2+10.0.LTS/bin/java",
        "jvmArgs" : [
        ],
        "jdkVersion" : "25.0.2",
        "vmName" : "OpenJDK 64-Bit Server VM",
        "vmVersion" : "25.0.2+10-LTS",
        "warmupIterations" : 3,
        "warmupTime" : "10 s",
        "warmupBatchSize" : 1,
        "measurementIterations" : 5,
        "measurementTime" : "10 s",
        "measurementBatchSize" : 1,
        "primaryMetric" : {
            "score" : 486782.66895190737,
            "scoreError" : 5924.613049614284,
            "scoreConfidence" : [
                480858.05590229307,
                492707.2820015217
            ],
            "scorePercentiles" : {
                "0.0" : 472594.2039700206,
                "50.0" : 488731.8776726364,
                "90.0" : 492709.68622414785,
                "95.0" : 493757.05550825153,
                "99.0" : 493757.05550825153,
                "99.9" : 493757.05550825153,
                "99.99" : 493757.05550825153,
                "99.999" : 493757.05550825153,
                "99.9999" : 493757.05550825153,
                "100.0" : 493757.05550825153
            },
            "scoreUnit" : "ops/s",
            "rawData" : [
                [
                    483439.47044879606,
                    483588.1038034622,
                    482670.7352758816,
                    480260.5484588427,
                    472594.2039700206
                ],
                [
                    489759.8096571718,
                    485681.32288568164,
                    489470.4921753771,
                    489686.3633786544,
                    491856.5163707363
                ],
                [
                    487429.72417886107,
                    490802.37045949197,
                    492011.4400347454,
                    493757.05550825153,
                    488731.8776726364
                ]
            ]
        },
        "secondaryMetrics" : {
        }
    }
]


